{"http://www.linkedin.com/in/amitsingh178": {"email": "amit@galvor.com", "verified": false}, "http://www.linkedin.com/in/sagar-p-97520311": {"email": "sagar@clanconnect.ai", "verified": false}, "http://www.linkedin.com/in/pooja2006": {"email": "pooja@aer.media", "verified": false}, "http://www.linkedin.com/in/ritwikmitra": {"email": "ritwik.mitra@verse.in", "verified": false}, "http://www.linkedin.com/in/ashish-bhambhani-8ab359266": {"email": "", "verified": false}, "http://www.linkedin.com/in/ucha-gviniashvili-11870a76": {"email": "ucha@settr.com", "verified": false}, "http://www.linkedin.com/in/sahil-bhagat-9b13099": {"email": "", "verified": false}, "http://www.linkedin.com/in/dark-username-650250261": {"email": "", "verified": false}, "http://www.linkedin.com/in/daequan-mens-038466195": {"email": "", "verified": false}, "http://www.linkedin.com/in/vikash-jain-889b9a49": {"email": "vikash.jain@verse.in", "verified": false}, "http://www.linkedin.com/in/vaibhav-thakkar-27681a2a": {"email": "vaibhav.thakkar@verse.in", "verified": false}, "http://www.linkedin.com/in/parag-pande-14a97971": {"email": "", "verified": false}, "http://www.linkedin.com/in/gauravbakshi1": {"email": "", "verified": false}, "http://www.linkedin.com/in/arunkolhapur": {"email": "arun.k@pantech.digital", "verified": false}, "http://www.linkedin.com/in/karandeep-singh-gujral-03130228": {"email": "karandeep.gujral@verse.in", "verified": false}, "http://www.linkedin.com/in/jackreeve1": {"email": "jack@go-nuggit.com", "verified": false}, "http://www.linkedin.com/in/dashsusanta": {"email": "", "verified": false}, "http://www.linkedin.com/in/arpit-bhawar-12a74141": {"email": "", "verified": false}, "http://www.linkedin.com/in/abhilashsomanchi": {"email": "abhilash.somanchi@verse.in", "verified": false}, "http://www.linkedin.com/in/abdullah-alkhanji-4b6b8a49": {"email": "", "verified": false}, "http://www.linkedin.com/in/maria-bersteneva": {"email": "maria.bersteneva@brandwatch.com", "verified": false}, "http://www.linkedin.com/in/akash-chaudhary-99733a197": {"email": "akash@fancall.in", "verified": false}, "http://www.linkedin.com/in/raynoldonline": {"email": "", "verified": false}, "http://www.linkedin.com/in/rodrigojun": {"email": "rodrigo.jun@infleux.co", "verified": false}, "http://www.linkedin.com/in/karlkathuria": {"email": "", "verified": false}, "http://www.linkedin.com/in/gstubbenhagen": {"email": "gary.stubbenhagen@bravebison.com", "verified": false}, "http://www.linkedin.com/in/paul-brothers-1b16a3": {"email": "paul@convosphere.com", "verified": false}, "http://www.linkedin.com/in/lawrence-richards-832537a": {"email": "", "verified": false}, "http://www.linkedin.com/in/kellie-matzen-b2787517": {"email": "kellie.matzen@influencer.com", "verified": false}, "http://www.linkedin.com/in/guilherme-schvartsman-b2b224317": {"email": "", "verified": false}, "http://www.linkedin.com/in/samelstob": {"email": "selstob@brandwatch.com", "verified": false}, "http://www.linkedin.com/in/dennis-dryden": {"email": "dennis.dryden@cision.com", "verified": false}, "http://www.linkedin.com/in/dafne-ulu%c3%a7%c4%b1nar-87504a54": {"email": "dafne.ulucinar@icmturkey.com", "verified": false}, "http://www.linkedin.com/in/vaisakh-babu-57387119": {"email": "vaisakh.babu@brandwatch.com", "verified": false}, "http://www.linkedin.com/in/matthew-kavanagh-7b7b2b24": {"email": "matthew.kavanagh@brandwatch.com", "verified": false}, "http://www.linkedin.com/in/jamie-pollitt-309b59104": {"email": "jamie@risingballers.co.uk", "verified": false}, "http://www.linkedin.com/in/sridhar-bandlamudi-a4a11177": {"email": "", "verified": false}, "http://www.linkedin.com/in/dorothy-john-%f0%9f%91%a9%f0%9f%8f%bf%e2%80%8d%f0%9f%92%bb-56200b140": {"email": "", "verified": false}, "http://www.linkedin.com/in/danielabbitt": {"email": "dan.abbitt@dizplai.com", "verified": false}, "http://www.linkedin.com/in/josefin-s-aa83a34b": {"email": "", "verified": false}, "http://www.linkedin.com/in/mark-clifford-84607086": {"email": "mark.clifford@dizplai.com", "verified": false}, "http://www.linkedin.com/in/alex-soskin-6b84a013": {"email": "", "verified": false}, "http://www.linkedin.com/in/ross-wilson-dev": {"email": "ross.wilson@bravebison.com", "verified": false}, "http://www.linkedin.com/in/andread74": {"email": "", "verified": false}, "http://www.linkedin.com/in/djef-riady-rifamole-8b836a175": {"email": "djef.rifamole@eyva.ai", "verified": false}, "http://www.linkedin.com/in/peter-berks-09bb2313": {"email": "peter.berks@stonegroup.co.uk", "verified": false}, "http://www.linkedin.com/in/makformula": {"email": "mak@formulamedia.com", "verified": false}, "http://www.linkedin.com/in/robertalbrecht74": {"email": "ra@facelift-bbt.com", "verified": false}, "http://www.linkedin.com/in/wilhelm-raider-60097156": {"email": "wilhelm.raider@eyva.ai", "verified": false}, "http://www.linkedin.com/in/katie-shamash-4b34a8171": {"email": "katie@overton.io", "verified": false}, "http://www.linkedin.com/in/euanadie": {"email": "euan@overton.io", "verified": false}, "http://www.linkedin.com/in/therahulprasad": {"email": "prasad@bobble.ai", "verified": false}, "http://www.linkedin.com/in/prasadankit": {"email": "prasad@bobble.ai", "verified": false}, "http://www.linkedin.com/in/forestfablesddn": {"email": "", "verified": false}, "http://www.linkedin.com/in/andreaswissel": {"email": "andreas.wissel@angulararchitects.io", "verified": false}, "http://www.linkedin.com/in/kunal-dawn": {"email": "kunal.dawn@bobble.ai", "verified": false}, "http://www.linkedin.com/in/norbert-dobrotka-05648a63": {"email": "", "verified": false}, "http://www.linkedin.com/in/guillaume-degrave-0961a432": {"email": "guillaume.degrave@dataventure.com", "verified": false}, "http://www.linkedin.com/in/sanjay-agrawal-00645815": {"email": "sanjay.agrawal@bobble.ai", "verified": false}, "http://www.linkedin.com/in/ranaharake": {"email": "rh@facelift-bbt.com", "verified": false}, "http://www.linkedin.com/in/louise-racine": {"email": "louise@lookoom.co", "verified": false}, "http://www.linkedin.com/in/adriana-theresia-fr%c3%a9d%c3%a9rica-7a830617b": {"email": "", "verified": false}, "http://www.linkedin.com/in/amadu-bah-46b2661b5": {"email": "", "verified": false}, "http://www.linkedin.com/in/syd-ouattara-525985169": {"email": "", "verified": false}, "http://www.linkedin.com/in/christinecazottes": {"email": "christine.cazottes@dataventure.com", "verified": false}, "http://www.linkedin.com/in/fabienyuos": {"email": "", "verified": false}, "http://www.linkedin.com/in/marcus-camen-75a01326": {"email": "marcus.camen@eviden.com", "verified": false}, "http://www.linkedin.com/in/jan-prochazka-consultant": {"email": "jan.prochazka@eviden.com", "verified": false}, "http://www.linkedin.com/in/vasco-gomes-eviden": {"email": "vasco.gomes@eviden.com", "verified": false}, "http://www.linkedin.com/in/ericeppe": {"email": "eric.eppe@eviden.com", "verified": false}, "http://www.linkedin.com/in/lars-middelhede-a726bb146": {"email": "", "verified": false}, "http://www.linkedin.com/in/pk2006mis": {"email": "prasad.kothari@hansacequity.com", "verified": false}, "http://www.linkedin.com/in/fchabaud": {"email": "florent.chabaud@eviden.com", "verified": false}, "http://www.linkedin.com/in/tackvan-robert-nsubuga-b40444359": {"email": "", "verified": false}, "http://www.linkedin.com/in/gsrivast": {"email": "gaurav@bobble.ai", "verified": false}, "http://www.linkedin.com/in/moritz-kriese-427096138": {"email": "", "verified": false}, "http://www.linkedin.com/in/daviddenjean": {"email": "david.denjean@eviden.com", "verified": false}, "http://www.linkedin.com/in/rajendra-engla-38a85746": {"email": "engla@bobble.ai", "verified": false}, "http://www.linkedin.com/in/davidcolin": {"email": "", "verified": false}, "http://www.linkedin.com/in/harjot-kaur-8499441b0": {"email": "", "verified": false}, "http://www.linkedin.com/in/ravikshh": {"email": "ravi.shharma@bobble.ai", "verified": false}, "http://www.linkedin.com/in/sebastianpedavoli": {"email": "sebastian@skedsocial.com", "verified": false}, "http://www.linkedin.com/in/danaevara": {"email": "dvara@redpoints.com", "verified": false}, "http://www.linkedin.com/in/vikas-giridhar-90a18530": {"email": "", "verified": false}, "http://www.linkedin.com/in/dtorrejon": {"email": "dtorrejon@redpoints.com", "verified": false}, "http://www.linkedin.com/in/tania-calvo-ba419027": {"email": "tcalvo@ravenpack.com", "verified": false}, "http://www.linkedin.com/in/nickpavord": {"email": "nick@windsorborn.com", "verified": false}, "http://www.linkedin.com/in/kaushik-parashar-a808a2124": {"email": "kaushik@bobble.ai", "verified": false}, "http://www.linkedin.com/in/raul-balanzino-a590b875": {"email": "rbalanzino@ravenpack.com", "verified": false}, "http://www.linkedin.com/in/raveena-kaushik-1717ab147": {"email": "", "verified": false}, "http://www.linkedin.com/in/think-tree-media-house-2aba9a176": {"email": "", "verified": false}, "http://www.linkedin.com/in/fidel-diaz-navarro-96193aa5": {"email": "", "verified": false}, "http://www.linkedin.com/in/daniel-benitez-14b60240": {"email": "dbenitez@ravenpack.com", "verified": false}, "http://www.linkedin.com/in/hemang-amin-a126145": {"email": "hemang.amin@bcci.tv", "verified": false}, "http://www.linkedin.com/in/rachid-sguiar-3b2758210": {"email": "", "verified": false}, "http://www.linkedin.com/in/gcleaves": {"email": "", "verified": false}, "http://www.linkedin.com/in/darraghoriordan": {"email": "darragh@skedsocial.com", "verified": false}, "http://www.linkedin.com/in/alexcanolp": {"email": "acano@ravenpack.com", "verified": false}, "http://www.linkedin.com/in/davidcasellas": {"email": "", "verified": false}, "http://www.linkedin.com/in/iamgauravmehrotra": {"email": "gaurav@webfries.com", "verified": false}, "http://www.linkedin.com/in/jamesrwstevenson": {"email": "jstevenson@ravenpack.com", "verified": false}, "http://www.linkedin.com/in/markokangrga": {"email": "mkangrga@ravenpack.com", "verified": false}, "http://www.linkedin.com/in/chloe-potts-26a486a2": {"email": "cpotts@ravenpack.com", "verified": false}, "http://www.linkedin.com/in/tameemalkharashi": {"email": "tameem@smartcode.sa", "verified": false}, "http://www.linkedin.com/in/alaa-almajhad": {"email": "alaa@tact.sa", "verified": false}, "http://www.linkedin.com/in/abdulaziz-alhaysony-8403a027a": {"email": "abdulaziz@smartcode.sa", "verified": false}, "http://www.linkedin.com/in/niki-russo-aa850243": {"email": "niki@imprint-social.com", "verified": false}, "http://www.linkedin.com/in/aleksandr-muzychenko-64165b33": {"email": "", "verified": false}, "http://www.linkedin.com/in/hadar-kess-873557198": {"email": "hadar@hamaniot.org", "verified": false}, "http://www.linkedin.com/in/altayli": {"email": "devrim.altayli@buzz.work", "verified": false}, "http://www.linkedin.com/in/warrisansari": {"email": "warris@muhimmaapp.com", "verified": false}, "http://www.linkedin.com/in/idan-rubinstein-737813114": {"email": "idanr@shout.market", "verified": false}, "http://www.linkedin.com/in/kathleenknowles": {"email": "kate@yellowdogpromotions.com", "verified": false}, "http://www.linkedin.com/in/sami-kade-b76b49136": {"email": "sami@farventure.com", "verified": false}, "http://www.linkedin.com/in/mahmoud-amr-b1b2282ab": {"email": "", "verified": false}, "http://www.linkedin.com/in/jeffsteep": {"email": "", "verified": false}, "http://www.linkedin.com/in/andrei-ionut-paduraru-92609027": {"email": "", "verified": false}, "http://www.linkedin.com/in/sameeh-selim-1750344": {"email": "sameeh@kairo.me", "verified": false}, "http://www.linkedin.com/in/sabrina-fenoglio-95749a29": {"email": "", "verified": false}, "http://www.linkedin.com/in/sarah-laitmas-harhad-a0b17a1a7": {"email": "", "verified": false}, "http://www.linkedin.com/in/matheus-alto%c3%a9-661276183": {"email": "maltoe@inbazz.com.br", "verified": false}, "http://www.linkedin.com/in/gabriel-viragine-42469944": {"email": "gabriel.viragine@vtracker.com.br", "verified": false}, "http://www.linkedin.com/in/leonardo-viragine-35863347": {"email": "leonardo.viragine@vtracker.com.br", "verified": false}, "http://www.linkedin.com/in/janet-cady-59b6261a9": {"email": "", "verified": false}, "http://www.linkedin.com/in/davineves": {"email": "davi@dzestudio.com.br", "verified": false}, "http://www.linkedin.com/in/thiagobarone": {"email": "thiago@ftwcomunicacao.com.br", "verified": false}, "http://www.linkedin.com/in/arthurjacintho": {"email": "ajacintho@inbazz.com.br", "verified": false}, "http://www.linkedin.com/in/murilo-koko": {"email": "murilo@agenciakoko.com.br", "verified": false}, "http://www.linkedin.com/in/fernandamalcher": {"email": "fernanda@tmcomunicacoes.com.br", "verified": false}, "http://www.linkedin.com/in/luz-adriana-torres-ramos-b2b3b94b": {"email": "luz.torres@bbdomexico.com", "verified": false}, "http://www.linkedin.com/in/camilo-plazas-michelsen-053495b": {"email": "camilo.plazas@bbdomexico.com", "verified": false}, "http://www.linkedin.com/in/natalia-andrea-saldarriaga-45460b27": {"email": "natalia.saldarriaga@fcbfrst.com", "verified": false}, "http://www.linkedin.com/in/jeffrey-ekeke-798014155": {"email": "", "verified": false}, "http://www.linkedin.com/in/nelsonfragoso": {"email": "nelson.fragoso@fcbfrst.com", "verified": false}, "http://www.linkedin.com/in/mercedes-valencia-64093b2b": {"email": "", "verified": false}, "http://www.linkedin.com/in/stevison-rocha-b44826212": {"email": "srocha@inbazz.com.br", "verified": false}, "http://www.linkedin.com/in/pablo-cavallo-4b73856": {"email": "pablo@wisecx.com", "verified": false}, "http://www.linkedin.com/in/panphilov": {"email": "", "verified": false}, "http://www.linkedin.com/in/gustavo-correa-26032215": {"email": "gustavo.correa@bbdomexico.com", "verified": false}, "http://www.linkedin.com/in/david-cardona-franco-1b063533": {"email": "", "verified": false}, "http://www.linkedin.com/in/andrea-lopezbarrios-199972334": {"email": "alopezbarrios@infobae.com", "verified": false}, "http://www.linkedin.com/in/nicolagomme": {"email": "nicola.gomme@theleap.io", "verified": false}, "http://www.linkedin.com/in/alix-stamatolatos-bertling-059398111": {"email": "", "verified": false}, "http://www.linkedin.com/in/joaquin-chervero-058365101": {"email": "joaquin.chervero@prosumia.la", "verified": false}, "http://www.linkedin.com/in/vikash-singh-7b830323": {"email": "", "verified": false}, "http://www.linkedin.com/in/pierre-valluy-51710b280": {"email": "", "verified": false}, "http://www.linkedin.com/in/ngrisales": {"email": "ngrisales@infobae.com", "verified": false}, "http://www.linkedin.com/in/paolaalvarado-fashionmanagement": {"email": "", "verified": false}, "http://www.linkedin.com/in/tdrach": {"email": "thomas@dreambaygroup.com", "verified": false}, "http://www.linkedin.com/in/michaelodai": {"email": "michael@mosaicventures.com", "verified": false}, "http://www.linkedin.com/in/zishan-ahmed-siddique-823b13247": {"email": "", "verified": false}, "http://www.linkedin.com/in/chervonagura": {"email": "matias@prosumia.la", "verified": false}, "http://www.linkedin.com/in/vinodn1": {"email": "vinod@unravelapp.com", "verified": false}, "http://www.linkedin.com/in/olivier-lasonder-88098517b": {"email": "lasonder@teleforwarding.com", "verified": false}, "http://www.linkedin.com/in/amplify-undefined-4aba00301": {"email": "", "verified": false}, "http://www.linkedin.com/in/jonathan-francisco-helver-6002aa296": {"email": "jfrancisco@infobae.com", "verified": false}, "http://www.linkedin.com/in/daniel-hadad-77a2b1175": {"email": "daniel@infobae.com", "verified": false}, "http://www.linkedin.com/in/michellesosnowski": {"email": "", "verified": false}, "http://www.linkedin.com/in/iamsagarmodi": {"email": "", "verified": false}, "http://www.linkedin.com/in/hamideh-iravani": {"email": "", "verified": false}, "http://www.linkedin.com/in/silke-bolms-345a669": {"email": "silke@silk-relations.com", "verified": false}, "http://www.linkedin.com/in/jobymathewjoseph": {"email": "joby@scoop.app", "verified": false}, "http://www.linkedin.com/in/alejandro-jattin-22977240": {"email": "alejandro@vibran.io", "verified": false}, "http://www.linkedin.com/in/ahmed-fourati-7487901ba": {"email": "ahmed@nclip.io", "verified": false}, "http://www.linkedin.com/in/emirpasic": {"email": "emir@layla.ai", "verified": false}, "http://www.linkedin.com/in/michel-chahda-62848066": {"email": "michel@talentplus.me", "verified": false}, "http://www.linkedin.com/in/luko-gjenero-02246012": {"email": "luko@layla.ai", "verified": false}, "http://www.linkedin.com/in/jueduardo": {"email": "", "verified": false}, "http://www.linkedin.com/in/bhavya-bhambhani-978b408b": {"email": "bhavyabhambhani@nmmarble.com", "verified": false}, "http://www.linkedin.com/in/manuela-villela-86858a16": {"email": "", "verified": false}, "http://www.linkedin.com/in/jos%c3%a9luismassa": {"email": "", "verified": false}, "http://www.linkedin.com/in/abidaboobaker": {"email": "abid@scoop.app", "verified": false}, "http://www.linkedin.com/in/%c3%b3scar-mengual-9191821b3": {"email": "", "verified": false}, "http://www.linkedin.com/in/vivian-gomez-409ab638": {"email": "vivian@scoop.app", "verified": false}, "http://www.linkedin.com/in/david-noguerol": {"email": "david@flowos.ai", "verified": false}, "http://www.linkedin.com/in/javier-gutierrez-490769b2": {"email": "j.gutierrez@vibran.io", "verified": false}, "http://www.linkedin.com/in/brunnorey": {"email": "brey@mohz.com.br", "verified": false}, "http://www.linkedin.com/in/monteiroshm": {"email": "", "verified": false}, "http://www.linkedin.com/in/benjamin-benattar-8868bb140": {"email": "", "verified": false}, "http://www.linkedin.com/in/vijaykumar-rajendran-4134a924": {"email": "", "verified": false}, "http://www.linkedin.com/in/alex-bennett-436609172": {"email": "alex@justmediahouse.com", "verified": false}, "http://www.linkedin.com/in/neil-taylor-5598b136": {"email": "ntaylor@global.com", "verified": false}, "http://www.linkedin.com/in/d%c3%a1vid-fab%c3%b3k-156261108": {"email": "", "verified": false}, "http://www.linkedin.com/in/ehtesham-ansari-916b8a136": {"email": "", "verified": false}, "http://www.linkedin.com/in/jens-klingelhofer": {"email": "jens.klingelhoefer@bookwire.de", "verified": false}, "http://www.linkedin.com/in/mogomotsi-mbisana-15583b34a": {"email": "", "verified": false}, "http://www.linkedin.com/in/gaston-ruiz-diaz": {"email": "gaston@adme.com.ar", "verified": false}, "http://www.linkedin.com/in/john-s-13a01823": {"email": "jsalat@cisco.com", "verified": false}, "http://www.linkedin.com/in/jessica-connell-1608b0114": {"email": "jessica.connell@global.com", "verified": false}, "http://www.linkedin.com/in/alexduncancto": {"email": "alex.duncan@global.com", "verified": false}, "http://www.linkedin.com/in/rachel-stoughton-crisp-50aa3879": {"email": "", "verified": false}, "http://www.linkedin.com/in/randomrock": {"email": "richard@lumiglobal.com", "verified": false}, "http://www.linkedin.com/in/madelein-ozok-mba-20134a11": {"email": "", "verified": false}, "http://www.linkedin.com/in/marc-harper-36a133a": {"email": "marc.harper@lumiglobal.com", "verified": false}, "http://www.linkedin.com/in/simon-rowe-2a94ab1": {"email": "simon.rowe@global.com", "verified": false}, "http://www.linkedin.com/in/samuel-rayment-65539242": {"email": "sam.rayment@global.com", "verified": false}, "http://www.linkedin.com/in/brettblackman": {"email": "", "verified": false}, "http://www.linkedin.com/in/gaditellez": {"email": "gadi.tellez@global.com", "verified": false}, "http://www.linkedin.com/in/bryan-johnson-73b53936": {"email": "", "verified": false}, "http://www.linkedin.com/in/oreste-andrea-banchieri-bb211a137": {"email": "", "verified": false}, "http://www.linkedin.com/in/pierre-antoine-capton-3094b4168": {"email": "pacapton@mediawan.eu", "verified": false}, "http://www.linkedin.com/in/holger-tuletz-96b6b76a": {"email": "holger.tuletz@bookwire.de", "verified": false}, "http://www.linkedin.com/in/joseph-craven-b3ba00b": {"email": "joseph@hybrid.co", "verified": false}, "http://www.linkedin.com/in/g-o-d-cdo-9b1745161": {"email": "", "verified": false}, "http://www.linkedin.com/in/rose-yara-241179a4": {"email": "", "verified": false}, "http://www.linkedin.com/in/althea-n-grant-1b0a8874": {"email": "", "verified": false}, "http://www.linkedin.com/in/brandon-de-faria-b78a526b": {"email": "", "verified": false}, "http://www.linkedin.com/in/laura-garcia-5b9571399": {"email": "laura@greengrants.org", "verified": false}, "http://www.linkedin.com/in/william-hurley-40711526": {"email": "", "verified": false}, "http://www.linkedin.com/in/arsyeo-tenefrancia-138017124": {"email": "", "verified": false}, "http://www.linkedin.com/in/niv-goffman-8a1552369": {"email": "", "verified": false}, "http://www.linkedin.com/in/sylvester-kamara-2635491a4": {"email": "", "verified": false}, "http://www.linkedin.com/in/ricardo-j-carrion-1b1410352": {"email": "", "verified": false}, "http://www.linkedin.com/in/ngugi-w-46508622": {"email": "", "verified": false}, "http://www.linkedin.com/in/edokpayi-godwin-b3859b152": {"email": "", "verified": false}, "http://www.linkedin.com/in/philip-martin-4202253a4": {"email": "pmartin@gbastudy.com", "verified": false}, "http://www.linkedin.com/in/michael-d-agostino-2495b97": {"email": "", "verified": false}, "http://www.linkedin.com/in/greggory-cates-22290630b": {"email": "", "verified": false}, "http://www.linkedin.com/in/leo-keyen-193a57184": {"email": "", "verified": false}, "http://www.linkedin.com/in/my-biglad-4a9bb9155": {"email": "", "verified": false}, "http://www.linkedin.com/in/zigar-mehta-a0981a253": {"email": "zmehta@cisco.com", "verified": false}, "http://www.linkedin.com/in/martha-walker-735b17144": {"email": "", "verified": false}, "http://www.linkedin.com/in/ghulammujtabaamr": {"email": "", "verified": false}, "http://www.linkedin.com/in/izu-udensi-b1a569382": {"email": "", "verified": false}, "http://www.linkedin.com/in/junk-junk-b00342373": {"email": "", "verified": false}, "http://www.linkedin.com/in/vincent-lowry-0aab34347": {"email": "vlowry@globalbetaadvisors.com", "verified": false}, "http://www.linkedin.com/in/csaba-n%c3%a9meth-681a59249": {"email": "", "verified": false}, "http://www.linkedin.com/in/raja-saqib-b31584353": {"email": "", "verified": false}, "http://www.linkedin.com/in/michael-bartl": {"email": "michael.bartl@tawny.ai", "verified": false}, "http://www.linkedin.com/in/liqin-zhang-8039b7375": {"email": "", "verified": false}, "http://www.linkedin.com/in/mathieu-yerle-a7578227": {"email": "myerle@intuiface.com", "verified": false}, "http://www.linkedin.com/in/wesley-ouzts-349a42167": {"email": "", "verified": false}, "http://www.linkedin.com/in/abdul-nafay-a4755438a": {"email": "", "verified": false}, "http://www.linkedin.com/in/jesus-garay-837206185": {"email": "", "verified": false}, "http://www.linkedin.com/in/muhammad-waseem-369a17295": {"email": "", "verified": false}, "http://www.linkedin.com/in/global-fastpaper-spa-214bb41ab": {"email": "", "verified": false}, "http://www.linkedin.com/in/varunsash": {"email": "", "verified": false}, "http://www.linkedin.com/in/mert-tunahan-9863b3261": {"email": "", "verified": false}, "http://www.linkedin.com/in/victoria-james-a86a6b3a8": {"email": "", "verified": false}, "http://www.linkedin.com/in/jeffery-donahue-84b960119": {"email": "", "verified": false}, "http://www.linkedin.com/in/jacob-gyldenk%c3%a6rne-8046635": {"email": "jacob@assemblyvoting.com", "verified": false}, "http://www.linkedin.com/in/luc-schoumacher-7a722a81": {"email": "lschoumacher@mediawan.eu", "verified": false}, "http://www.linkedin.com/in/lucy-crowe-53103459": {"email": "lucy.crowe@theaudienceagency.org", "verified": false}, "http://www.linkedin.com/in/matthew-daniel-324584a8": {"email": "matthew.daniel@global.com", "verified": false}, "http://www.linkedin.com/in/christian-lindemann-97a93588": {"email": "christian.lindemann@bookwire.de", "verified": false}, "http://www.linkedin.com/in/harleyayers": {"email": "harley.ayers@global.com", "verified": false}, "http://www.linkedin.com/in/christy-johnston": {"email": "christy.johnston@global.com", "verified": false}, "http://www.linkedin.com/in/thomaselliotwalker": {"email": "thomas.walker@global.com", "verified": false}, "http://www.linkedin.com/in/cfrance": {"email": "chris.france@theaudienceagency.org", "verified": false}, "http://www.linkedin.com/in/shaun-palmer-8857935a": {"email": "shaun.palmer@matchroom.com", "verified": false}, "http://www.linkedin.com/in/bwalker1994": {"email": "ben.walker@global.com", "verified": false}, "http://www.linkedin.com/in/schmelck": {"email": "dschmelck@mediawan.eu", "verified": false}, "http://www.linkedin.com/in/paul-johnson-3a5220155": {"email": "paul.johnson@global.com", "verified": false}, "http://www.linkedin.com/in/markasquith": {"email": "mark@thisisglobal.com", "verified": false}, "http://www.linkedin.com/in/larae-mardesic-bechmann-3440a8a": {"email": "", "verified": false}, "http://www.linkedin.com/in/sonia-esteban-roba-50691327": {"email": "sonia.esteban@global.com", "verified": false}, "http://www.linkedin.com/in/nick-schofield-frsn-2378995": {"email": "", "verified": false}, "http://www.linkedin.com/in/richarddickatkins": {"email": "", "verified": false}, "http://www.linkedin.com/in/abdallah-chouaf-73a458277": {"email": "", "verified": false}, "http://www.linkedin.com/in/rubybhattal": {"email": "", "verified": false}, "http://www.linkedin.com/in/suzanne-ryder-richardson-501a7714": {"email": "sryder@global.com", "verified": false}, "http://www.linkedin.com/in/liam-mcallister-85b550116": {"email": "liam.mcallister@global.com", "verified": false}, "http://www.linkedin.com/in/louis-cyrille-trebuchet-4a81107": {"email": "louis-cyrille.trebuchet@afp.com", "verified": false}, "http://www.linkedin.com/in/anna-brown-hrd": {"email": "anna.brown@global.com", "verified": false}, "http://www.linkedin.com/in/simon-price-926424a": {"email": "simon.price@thisisglobal.com", "verified": false}, "http://www.linkedin.com/in/peter-cropley-b7150178": {"email": "peter.cropley@thisisglobal.com", "verified": false}, "http://www.linkedin.com/in/cedric-rouse-0aaa1b16": {"email": "cedric.rouse@global.com", "verified": false}, "http://www.linkedin.com/in/paul-etherington-2b183225": {"email": "paul@global.com", "verified": false}, "http://www.linkedin.com/in/marcosaal": {"email": "saal@horizont.net", "verified": false}, "http://www.linkedin.com/in/giordana-pierantoni-318b26168": {"email": "", "verified": false}, "http://www.linkedin.com/in/delphine-cazaux-89779413": {"email": "dcazaux@mediawan.eu", "verified": false}, "http://www.linkedin.com/in/bmasse": {"email": "benjamin.masse@tritondigital.com", "verified": false}, "http://www.linkedin.com/in/cliff-walker-52592b382": {"email": "", "verified": false}, "http://www.linkedin.com/in/paulmccormack1975": {"email": "paul.mccormack@global.com", "verified": false}, "http://www.linkedin.com/in/shaunhill-schwartz-064969267": {"email": "", "verified": false}, "http://www.linkedin.com/in/miguelzambrana": {"email": "mzambrana@npaw.com", "verified": false}, "http://www.linkedin.com/in/gowtham-krishna-p-585740210": {"email": "gowtham@marketbytes.in", "verified": false}, "http://www.linkedin.com/in/bnca-69aaa11a6": {"email": "", "verified": false}, "http://www.linkedin.com/in/prince-bang-888498103": {"email": "", "verified": false}, "http://www.linkedin.com/in/yurdana-burgoa-valtierra-aa117a19": {"email": "yurdana@lasttour.org", "verified": false}, "http://www.linkedin.com/in/jrosso": {"email": "john.rosso@tritondigital.com", "verified": false}, "http://www.linkedin.com/in/ashish-sedani": {"email": "ashish.sedani@neoniche.com", "verified": false}, "http://www.linkedin.com/in/marketbytes-sales-122abb293": {"email": "", "verified": false}, "http://www.linkedin.com/in/rahulbajaj6": {"email": "rahul.bajaj@pocketaces.in", "verified": false}, "http://www.linkedin.com/in/michielbugher": {"email": "michiel.bugher@tritondigital.com", "verified": false}, "http://www.linkedin.com/in/sharontaylorau": {"email": "sharon.taylor@tritondigital.com", "verified": false}, "http://www.linkedin.com/in/anantha-krishnan-84684130b": {"email": "", "verified": false}, "http://www.linkedin.com/in/felipe-jaramillo-caro": {"email": "felipe@lasttour.org", "verified": false}, "http://www.linkedin.com/in/ryantrutch": {"email": "ryan@p-1.me", "verified": false}, "http://www.linkedin.com/in/sonaryogesh": {"email": "yogesh.sonar@neoniche.com", "verified": false}, "http://www.linkedin.com/in/sagarsinghchauhan": {"email": "sagar@communiqueindia.com", "verified": false}, "http://www.linkedin.com/in/saif-rashid-al-noaimi-7b0474147": {"email": "saif.alnoaimi@ethara.com", "verified": false}, "http://www.linkedin.com/in/karanmurarka": {"email": "karan@karastudios.com", "verified": false}, "http://www.linkedin.com/in/fmadia": {"email": "fabio.madia@btsbrasil.tv", "verified": false}, "http://www.linkedin.com/in/sam-barnett-366b58356": {"email": "sambarnett@mbc.net", "verified": false}, "http://www.linkedin.com/in/maximiliano-cabrera-40a10616": {"email": "mcabrera@torneos.com", "verified": false}, "http://www.linkedin.com/in/jenny-tan-681b6065": {"email": "jenny@toorly.com", "verified": false}, "http://www.linkedin.com/in/yun-seo-b213b6216": {"email": "", "verified": false}, "http://www.linkedin.com/in/abed-almoin-homsi-22816913b": {"email": "", "verified": false}, "http://www.linkedin.com/in/david-ben-basat-7889a9159": {"email": "", "verified": false}, "http://www.linkedin.com/in/olivierbachelier": {"email": "olivier.bachelier@mbc.net", "verified": false}, "http://www.linkedin.com/in/dominic-farrell-6576ba": {"email": "dominic.farrell@mbc.net", "verified": false}, "http://www.linkedin.com/in/jorge-dibildox-valls-a62aa83": {"email": "jdibildox@grupoexpansion.com", "verified": false}, "http://www.linkedin.com/in/tuncayhatipoglu": {"email": "", "verified": false}, "http://www.linkedin.com/in/marcelorizzi": {"email": "mrizzi@grupoclarin.com", "verified": false}, "http://www.linkedin.com/in/rundkhalaf": {"email": "", "verified": false}, "http://www.linkedin.com/in/haidarshukri": {"email": "haidar.shukry@ethara.com", "verified": false}, "http://www.linkedin.com/in/damian-alejandro-molinari-30025622": {"email": "damian@mediainbox.net", "verified": false}, "http://www.linkedin.com/in/juan-duche-4537b7106": {"email": "jduche@torneos.com", "verified": false}, "http://www.linkedin.com/in/leonardo-berm%c3%badez-a43a6789": {"email": "", "verified": false}, "http://www.linkedin.com/in/felipe-tobalina-4b2012206": {"email": "ftobalina@torneos.com", "verified": false}, "http://www.linkedin.com/in/matias-ocampo-3a0b8b27": {"email": "", "verified": false}, "http://www.linkedin.com/in/guillermo-testa-5a9485333": {"email": "gtesta@artear.com", "verified": false}, "http://www.linkedin.com/in/mario-cuomo-3003a250": {"email": "mcuomo@artear.com", "verified": false}, "http://www.linkedin.com/in/isaurralde-javier-254a1a115": {"email": "javier.isaurralde@torneos.com", "verified": false}, "http://www.linkedin.com/in/orkanarikan": {"email": "", "verified": false}, "http://www.linkedin.com/in/elena-s%c3%a1enz-guerra-59b155293": {"email": "", "verified": false}, "http://www.linkedin.com/in/aurelio-francesco-54a425128": {"email": "", "verified": false}, "http://www.linkedin.com/in/marcelo-capiello-48757263": {"email": "", "verified": false}, "http://www.linkedin.com/in/ilhan-%c5%9feng%c3%bcl-734377351": {"email": "", "verified": false}, "http://www.linkedin.com/in/darryllbayes": {"email": "darryll@thing-or-two.com", "verified": false}, "http://www.linkedin.com/in/biggerdata": {"email": "lukasz.kapusniak@cloudtechnologies.pl", "verified": false}, "http://www.linkedin.com/in/benhookway": {"email": "ben@relativeinsight.com", "verified": false}, "http://www.linkedin.com/in/kearneyrussell": {"email": "russell@encoredigitalmedia.net", "verified": false}, "http://www.linkedin.com/in/bahaa-al-zyoud-25117a31": {"email": "bahaa@spica.media", "verified": false}, "http://www.linkedin.com/in/neil-barber-49641926": {"email": "neil.barber@interactcc.com", "verified": false}, "http://www.linkedin.com/in/jillian-heuer-2a13643a2": {"email": "", "verified": false}, "http://www.linkedin.com/in/mazi-ogbonna-61632723": {"email": "", "verified": false}, "http://www.linkedin.com/in/maferres": {"email": "maria@themixglobal.com", "verified": false}, "http://www.linkedin.com/in/tashwalker1": {"email": "tash@themixglobal.com", "verified": false}, "http://www.linkedin.com/in/phil-greenwood-50408051": {"email": "phil@relativeinsight.com", "verified": false}, "http://www.linkedin.com/in/frank-reynolds-13b7a43a3": {"email": "", "verified": false}, "http://www.linkedin.com/in/alejandropablotkachuk": {"email": "atkachuk@atlantida.com.ar", "verified": false}, "http://www.linkedin.com/in/abr-sport-1389331a1": {"email": "platform@pentagroup.com", "verified": false}, "http://www.linkedin.com/in/natalia-rachlin-40a761250": {"email": "natalia@mothertonguemagazine.com", "verified": false}, "http://www.linkedin.com/in/eyelanksburycreative": {"email": "", "verified": false}, "http://www.linkedin.com/in/joe-green-25abb8205": {"email": "", "verified": false}, "http://www.linkedin.com/in/stuart-findlay-47517689": {"email": "stuart.findlay@walnutunlimited.com", "verified": false}, "http://www.linkedin.com/in/rosecallaghan": {"email": "", "verified": false}, "http://www.linkedin.com/in/mikki-shan-51a2bb138": {"email": "", "verified": false}, "http://www.linkedin.com/in/alex-ross-redtorch": {"email": "alex.ross@redtorch.co", "verified": false}, "http://www.linkedin.com/in/benjaminjamesduncan": {"email": "benjamin.duncan@tribalworldwide.co.uk", "verified": false}, "http://www.linkedin.com/in/marcushickman1": {"email": "marcus@levellr.com", "verified": false}, "http://www.linkedin.com/in/olly-blitz-b05a7689": {"email": "olly@20ten.co.uk", "verified": false}, "http://www.linkedin.com/in/daniel-lewis-46959585": {"email": "danl@encoredigitalmedia.net", "verified": false}, "http://www.linkedin.com/in/rajesh-nair-68a53811": {"email": "rajesh@tonicworldwide.com", "verified": false}, "http://www.linkedin.com/in/florence-hussenot-2837392a5": {"email": "fhussenot@adwise-research.com", "verified": false}, "http://www.linkedin.com/in/tgsrinivasan": {"email": "tgs@pixel-studios.com", "verified": false}, "http://www.linkedin.com/in/reda-aboulkacem": {"email": "reda@netino.com", "verified": false}, "http://www.linkedin.com/in/kim-singh-4195644b": {"email": "", "verified": false}, "http://www.linkedin.com/in/lauren-a-whitehurst-433a2310": {"email": "lauren@sfreporter.com", "verified": false}, "http://www.linkedin.com/in/nicolas-riou-brainvalue": {"email": "nriou@brainvalue.com", "verified": false}, "http://www.linkedin.com/in/pravin-joshi-6023aa8a": {"email": "", "verified": false}, "http://www.linkedin.com/in/filiparolo": {"email": "", "verified": false}, "http://www.linkedin.com/in/pierre-morel-433568": {"email": "", "verified": false}, "http://www.linkedin.com/in/maximecohendet": {"email": "mc@reseau-entreprendre.org", "verified": false}, "http://www.linkedin.com/in/andr%c3%a9-ren%c3%a9-na%c3%afm-4787ab192": {"email": "", "verified": false}, "http://www.linkedin.com/in/christinebonnin": {"email": "cbonnin@akio.com", "verified": false}, "http://www.linkedin.com/in/talktariqul": {"email": "", "verified": false}, "http://www.linkedin.com/in/robert-h-webb-b91319253": {"email": "", "verified": false}, "http://www.linkedin.com/in/krisscreol": {"email": "mk@stan-studios.com", "verified": false}, "http://www.linkedin.com/in/sudish-b-86227011": {"email": "sudish@tonicworldwide.com", "verified": false}, "http://www.linkedin.com/in/samuel-rumeur-352855123": {"email": "srumeur@akio.com", "verified": false}, "http://www.linkedin.com/in/malhotrarishi": {"email": "rishi@teamcafeteria.com", "verified": false}, "http://www.linkedin.com/in/clintob": {"email": "clint@teamcafeteria.com", "verified": false}, "http://www.linkedin.com/in/grubaknielsen": {"email": "henrik.grubak@stanworldwide.com", "verified": false}, "http://www.linkedin.com/in/lavkumar": {"email": "lav.kumar@xebecindia.com", "verified": false}, "http://www.linkedin.com/in/felicityfellows": {"email": "felicity@stanworldwide.com", "verified": false}, "http://www.linkedin.com/in/oleg-vorontsov-phd-586b24152": {"email": "o.vorontsov@dezzai.com", "verified": false}, "http://www.linkedin.com/in/pradip-kumar-mandal-3b99682": {"email": "pradipkumar.mandal@futurlytic.com", "verified": false}, "http://www.linkedin.com/in/ryan-j-peterson-4b21b75": {"email": "ryan@teamcafeteria.com", "verified": false}, "http://www.linkedin.com/in/athikurrehman": {"email": "athik.ansari@cerebratesolutions.in", "verified": false}, "http://www.linkedin.com/in/akanand": {"email": "amit@loqal.ai", "verified": false}, "http://www.linkedin.com/in/silversteinmark": {"email": "mark@teamcafeteria.com", "verified": false}, "http://www.linkedin.com/in/rohit-bhat-65786929": {"email": "rohit@experiencecommerce.com", "verified": false}, "http://www.linkedin.com/in/leeann-sheely-4188b949": {"email": "leeann@teamcafeteria.com", "verified": false}, "http://www.linkedin.com/in/luis-m-velasco-quijano-96128b46": {"email": "l.velasco@dezzai.com", "verified": false}, "http://www.linkedin.com/in/jo-grierson-b41a0213": {"email": "jo.grierson@onegreenbean.com", "verified": false}, "http://www.linkedin.com/in/anirbanbrandwind": {"email": "anirban@brandwind.in", "verified": false}, "http://www.linkedin.com/in/larshemming": {"email": "lars@heroiq.co", "verified": false}, "http://www.linkedin.com/in/mohamed-amin-859b0826": {"email": "mamin@sphere-consulting.com", "verified": false}, "http://www.linkedin.com/in/juliangarciatorres": {"email": "julian.garcia@relevanttraffic.com", "verified": false}, "http://www.linkedin.com/in/regan-rodrigues": {"email": "regan@yardstick-marketing.com", "verified": false}, "http://www.linkedin.com/in/shadabkhan8484": {"email": "shadab.khan@cerebratesolutions.in", "verified": false}, "http://www.linkedin.com/in/nataliamelo": {"email": "natalia.melo@nr7.ag", "verified": false}, "http://www.linkedin.com/in/ram-naresh-jha-35285a51": {"email": "", "verified": false}, "http://www.linkedin.com/in/wael-anwar-a51b1026": {"email": "wanwar@sphere-consulting.com", "verified": false}, "http://www.linkedin.com/in/amir-r-490a52355": {"email": "ar@xdbscorp.com", "verified": false}, "http://www.linkedin.com/in/julia-hussein": {"email": "", "verified": false}, "http://www.linkedin.com/in/ourielboiria": {"email": "ouriel@kinoba.fr", "verified": false}, "http://www.linkedin.com/in/sajad-thaer-obaed-65abb0212": {"email": "", "verified": false}, "http://www.linkedin.com/in/tinta-nicolae-b470508a": {"email": "", "verified": false}, "http://www.linkedin.com/in/lucas-rangel-281492164": {"email": "lucasrangel@lrcontents.com.br", "verified": false}, "http://www.linkedin.com/in/shakeel-ahmed-7b3819104": {"email": "", "verified": false}, "http://www.linkedin.com/in/dariela-fern%c3%a1ndez-turcios-941480203": {"email": "", "verified": false}, "http://www.linkedin.com/in/swarnim-pradhan-828878144": {"email": "", "verified": false}, "http://www.linkedin.com/in/amanda-abr%c3%a3o-1b2a6325": {"email": "amanda@aamarelo.com.br", "verified": false}, "http://www.linkedin.com/in/mariane-maciel": {"email": "mariane@aamarelo.com.br", "verified": false}, "http://www.linkedin.com/in/carol-kainnan-1b94a8158": {"email": "", "verified": false}, "http://www.linkedin.com/in/marwanebejgane": {"email": "marwane@amarelo.fr", "verified": false}, "http://www.linkedin.com/in/kuldeep-pandey-6aa03050": {"email": "", "verified": false}, "http://www.linkedin.com/in/gersonribeiro": {"email": "gerson@biosphera.net", "verified": false}, "http://www.linkedin.com/in/mitch-lord-b508713": {"email": "", "verified": false}, "http://www.linkedin.com/in/denis-vidigal-37011730": {"email": "", "verified": false}, "http://www.linkedin.com/in/tere-sordo-77420732": {"email": "tere@morfina.mx", "verified": false}, "http://www.linkedin.com/in/stiwar-garcia-9661095b": {"email": "stiwar.garcia@brm.com.co", "verified": false}, "http://www.linkedin.com/in/ana-maria-lozano-5aa61614": {"email": "ana.lozano@dipaolalatina.com", "verified": false}, "http://www.linkedin.com/in/eduardo-fritsch-a9bb3a12": {"email": "fritsch@morfina.mx", "verified": false}, "http://www.linkedin.com/in/jesushoyos": {"email": "jesus.hoyos@solvisconsulting.com", "verified": false}, "http://www.linkedin.com/in/therese-baradhy-5b872b17": {"email": "", "verified": false}, "http://www.linkedin.com/in/nelson-david-acero-cantor-7711b41b2": {"email": "", "verified": false}, "http://www.linkedin.com/in/damiansuarez": {"email": "damian.suarez@megaresearch.net", "verified": false}, "http://www.linkedin.com/in/mattikokkola": {"email": "matti.kokkola@trademarknow.com", "verified": false}, "http://www.linkedin.com/in/simpleigh": {"email": "", "verified": false}, "http://www.linkedin.com/in/mauricio-alberto-forero-matallana-45885559": {"email": "", "verified": false}, "http://www.linkedin.com/in/eliezer-enriquez-b9519152": {"email": "e.enriquez@difraxion.com", "verified": false}, "http://www.linkedin.com/in/chasesrichards": {"email": "chase.richards@corsearch.com", "verified": false}, "http://www.linkedin.com/in/ankush-bagmar-digital-marketer": {"email": "ankush@digitalizetheglobe.com", "verified": false}, "http://www.linkedin.com/in/carlos-medina-ramirez-03bb28202": {"email": "", "verified": false}, "http://www.linkedin.com/in/jrbpearson": {"email": "james.pearson@corsearch.com", "verified": false}, "http://www.linkedin.com/in/anand-kumar-r-2813b246": {"email": "anandkumar@linkedin.com", "verified": false}, "http://www.linkedin.com/in/patricia-finoti-58055921": {"email": "patricia.finoti@missionbrasil.com.br", "verified": false}, "http://www.linkedin.com/in/asalmin": {"email": "alexey.salmin@navee.co", "verified": false}, "http://www.linkedin.com/in/mazlumagar": {"email": "mazlum.agar@brandefense.io", "verified": false}, "http://www.linkedin.com/in/sergio-teubal-647188104": {"email": "sergio@orishinal.com", "verified": false}, "http://www.linkedin.com/in/manoharkashyap": {"email": "manohar@gfactors.co.in", "verified": false}, "http://www.linkedin.com/in/thibault-renouf-partoo": {"email": "thibault.renouf@partoo.fr", "verified": false}, "http://www.linkedin.com/in/jonasbru": {"email": "jonas.bru-monserrat@partoo.co", "verified": false}, "http://www.linkedin.com/in/bahadirkinali": {"email": "bahadir.kinali@brandefense.io", "verified": false}, "http://www.linkedin.com/in/goktugeren": {"email": "goktug.eren@brandefense.io", "verified": false}, "http://www.linkedin.com/in/pierrehofman": {"email": "", "verified": false}, "http://www.linkedin.com/in/silvana-frenquel-845636b": {"email": "silvana.frenquel@orishinal.com", "verified": false}, "http://www.linkedin.com/in/julius-stobbs-24b50814": {"email": "julius.stobbs@iamstobbs.com", "verified": false}, "http://www.linkedin.com/in/danielle-de-jager-b33423292": {"email": "danielle.dejager@corsearch.com", "verified": false}, "http://www.linkedin.com/in/eleni-leila-nicolaidis-303849158": {"email": "eleni.nicolaidis@corsearch.com", "verified": false}, "http://www.linkedin.com/in/brianconchuratt": {"email": "", "verified": false}, "http://www.linkedin.com/in/jonah-ellin-4585532": {"email": "", "verified": false}, "http://www.linkedin.com/in/srinivas-m-r-b3a8a717": {"email": "srinivas@atonnetwork.com", "verified": false}, "http://www.linkedin.com/in/jonathan-jaggers-68117b12": {"email": "jonathan.jaggers@corsearch.com", "verified": false}, "http://www.linkedin.com/in/kiran-chavan-20207355": {"email": "", "verified": false}, "http://www.linkedin.com/in/jonathanlevitre": {"email": "jonathan.levitre@partoo.fr", "verified": false}, "http://www.linkedin.com/in/hakaneryavuz": {"email": "hakan.eryavuz@brandefense.io", "verified": false}, "http://www.linkedin.com/in/meghan-medeiros": {"email": "meghan.medeiros@corsearch.com", "verified": false}, "http://www.linkedin.com/in/lewiswhiting": {"email": "lewis@iaido.ai", "verified": false}, "http://www.linkedin.com/in/karl-florida-a097215": {"email": "", "verified": false}, "http://www.linkedin.com/in/ankit-mishra-99375437": {"email": "mishraa@google.com", "verified": false}, "http://www.linkedin.com/in/ilnitskaya": {"email": "svetlana.ilnitskaya@corsearch.com", "verified": false}, "http://www.linkedin.com/in/akhildev": {"email": "akhil@lsd.productions", "verified": false}, "http://www.linkedin.com/in/darine-urabi-kassab-bashi-76010713b": {"email": "", "verified": false}, "http://www.linkedin.com/in/yashbhatnagar": {"email": "", "verified": false}, "http://www.linkedin.com/in/kartikey19": {"email": "kartikey@ylytic.com", "verified": false}, "http://www.linkedin.com/in/gsn-aditya-13819b3a": {"email": "aditya@eloelo.in", "verified": false}, "http://www.linkedin.com/in/balam20": {"email": "mani@ventesavenues.in", "verified": false}, "http://www.linkedin.com/in/cristian-lara-a2668a62": {"email": "", "verified": false}, "http://www.linkedin.com/in/niloufer-dundh-53980313": {"email": "nilouferdundh@ventesavenues.in", "verified": false}, "http://www.linkedin.com/in/ricardo-lu%c3%ads-ribeiro-62b14551": {"email": "ricardo.ribeiro@lounges.tv", "verified": false}, "http://www.linkedin.com/in/nigeljjohnson": {"email": "", "verified": false}, "http://www.linkedin.com/in/aamir-shaikh-ba097a50": {"email": "aamir@adxpoint.com", "verified": false}, "http://www.linkedin.com/in/danielward72": {"email": "daniel@rerightmusic.com", "verified": false}, "http://www.linkedin.com/in/thomas-breslin-3536a53a": {"email": "thomas@rerightmusic.com", "verified": false}, "http://www.linkedin.com/in/anil-srivatsa-b0a7543": {"email": "anil@sochcast.com", "verified": false}, "http://www.linkedin.com/in/jamesturner247": {"email": "jt@delineate.ai", "verified": false}, "http://www.linkedin.com/in/nadavshmuel": {"email": "nadav@precise.tv", "verified": false}, "http://www.linkedin.com/in/dankl": {"email": "christian@precisify.com", "verified": false}, "http://www.linkedin.com/in/yevheniia-buhaienko-zimmerman": {"email": "", "verified": false}, "http://www.linkedin.com/in/niamhfitzpatrick": {"email": "niamh.fitzpatrick@pureprofile.com", "verified": false}, "http://www.linkedin.com/in/pyush-agrawal-b6a788335": {"email": "", "verified": false}, "http://www.linkedin.com/in/markjbenjamin": {"email": "mark.benjamin@convertr.io", "verified": false}, "http://www.linkedin.com/in/kanhaiyarajpandey": {"email": "", "verified": false}, "http://www.linkedin.com/in/tanguy-ducrocq-4b580728a": {"email": "", "verified": false}, "http://www.linkedin.com/in/mesheppard": {"email": "melinda@pureprofile.com", "verified": false}, "http://www.linkedin.com/in/linkedinrichardparsons": {"email": "richard@trueagency.com", "verified": false}, "http://www.linkedin.com/in/john-griffin-5a297540": {"email": "john@pureprofile.com", "verified": false}, "http://www.linkedin.com/in/fabbarone": {"email": "fabio.barone@dataprev.gov.br", "verified": false}, "http://www.linkedin.com/in/sam-r-brown": {"email": "sbrown@precisify.com", "verified": false}, "http://www.linkedin.com/in/anujsharma80": {"email": "asharma@precisify.com", "verified": false}, "http://www.linkedin.com/in/georgeageorgopoulos": {"email": "ggeorgopoulos@pureprofile.com", "verified": false}, "http://www.linkedin.com/in/sergiogrinbaum": {"email": "sergio@think-thanks.com", "verified": false}, "http://www.linkedin.com/in/che-mainwaring": {"email": "", "verified": false}, "http://www.linkedin.com/in/gayathri-maalige-183620166": {"email": "gayathri@catalysts.team", "verified": false}, "http://www.linkedin.com/in/peter-stoeckl": {"email": "peter@precisify.com", "verified": false}, "http://www.linkedin.com/in/julianaferris": {"email": "juliana.ferris@dataprev.gov.br", "verified": false}, "http://www.linkedin.com/in/chenivan1": {"email": "ivan.chen@pureprofile.com", "verified": false}, "http://www.linkedin.com/in/dr-wilona-annunciation-249528115": {"email": "", "verified": false}, "http://www.linkedin.com/in/sugumarsupra": {"email": "", "verified": false}, "http://www.linkedin.com/in/rodrigo-assump%c3%a7%c3%a3o-289359122": {"email": "", "verified": false}, "http://www.linkedin.com/in/katiemay-gardner-a0950258": {"email": "katiemay.gardner@pureprofile.com", "verified": false}, "http://www.linkedin.com/in/aushim-krishan": {"email": "", "verified": false}, "http://www.linkedin.com/in/aleksandar-nikolic-03964b134": {"email": "aleksandar.nikolic@fairplaysportsmedia.com", "verified": false}, "http://www.linkedin.com/in/ayub-subhaniya-7632a4112": {"email": "ayub.subhaniya@gocommotion.com", "verified": false}, "http://www.linkedin.com/in/laurentgivaudan": {"email": "l.givaudan@aplusaresearch.com", "verified": false}, "http://www.linkedin.com/in/daniel-alves-sant-ana": {"email": "daniel.ana@dataprev.gov.br", "verified": false}, "http://www.linkedin.com/in/keith-buzzard-72a5a848": {"email": "keith.buzzard@pgitl.com", "verified": false}, "http://www.linkedin.com/in/vasantsrinivasan": {"email": "vsrinivasan@gocommotion.com", "verified": false}, "http://www.linkedin.com/in/sonia-garcia-b248a030a": {"email": "", "verified": false}, "http://www.linkedin.com/in/chinnikrishnanck": {"email": "chinni@ninestars.in", "verified": false}, "http://www.linkedin.com/in/cornelius-ajibola-9853404a": {"email": "", "verified": false}, "http://www.linkedin.com/in/thomas-spagnol-3344b045": {"email": "", "verified": false}, "http://www.linkedin.com/in/samy-trigui-357bbb3": {"email": "samy.trigui@fairplaysportsmedia.com", "verified": false}, "http://www.linkedin.com/in/anne-cellyne-4a754b49": {"email": "", "verified": false}, "http://www.linkedin.com/in/sam-stratton-a023aa35": {"email": "sam@commotion.agency", "verified": false}, "http://www.linkedin.com/in/des-kane-2a807b20": {"email": "d.kane@proxymity.io", "verified": false}, "http://www.linkedin.com/in/pierre-pigeon-987a709": {"email": "p.pigeon@aplusaresearch.com", "verified": false}, "http://www.linkedin.com/in/rizwan-jamil-19652a47": {"email": "", "verified": false}, "http://www.linkedin.com/in/sagar-savaliya-0825a3128": {"email": "ssavaliya@gocommotion.com", "verified": false}, "http://www.linkedin.com/in/gema-parlange-iturmendi-25731118": {"email": "g.parlangeiturmendi@aplusaresearch.com", "verified": false}, "http://www.linkedin.com/in/mbilge": {"email": "mustafa@dengage.com", "verified": false}, "http://www.linkedin.com/in/sam-cockburn-a993388a": {"email": "sam@sendtrumpet.com", "verified": false}, "http://www.linkedin.com/in/kishin-karra": {"email": "kkarra@gocommotion.com", "verified": false}, "http://www.linkedin.com/in/harsh-sehgal-5886a1207": {"email": "", "verified": false}, "http://www.linkedin.com/in/ilariagatti": {"email": "ilaria@sendtrumpet.com", "verified": false}, "http://www.linkedin.com/in/tu%c4%9f%c3%a7e-esenkar-temel-87192732": {"email": "tugce@dengage.com", "verified": false}, "http://www.linkedin.com/in/prashantakhawat": {"email": "prashant.a@ninestars.in", "verified": false}, "http://www.linkedin.com/in/jonathan-branagan-04978577": {"email": "j.branagan@proxymity.io", "verified": false}, "http://www.linkedin.com/in/jonathan-dunbar-9b308857": {"email": "jonathan@valinorintelligence.com", "verified": false}, "http://www.linkedin.com/in/raviprasadbv": {"email": "ravi.bv@ninestars.in", "verified": false}, "http://www.linkedin.com/in/gary-alexander-257690266": {"email": "", "verified": false}, "http://www.linkedin.com/in/ichiragshah": {"email": "cshah@gocommotion.com", "verified": false}, "http://www.linkedin.com/in/nic-parry-58683111": {"email": "nic@hook.co", "verified": false}, "http://www.linkedin.com/in/alex-welsby-3772395a": {"email": "", "verified": false}, "http://www.linkedin.com/in/julian-matthews-249b94": {"email": "julian.matthews@targetgroup.com", "verified": false}, "http://www.linkedin.com/in/murat-dar%c3%a7%c4%b1n-aa60ab1b": {"email": "murat.darcin@dengage.com", "verified": false}, "http://www.linkedin.com/in/rohit-garg-84536853": {"email": "", "verified": false}, "http://www.linkedin.com/in/markseemann": {"email": "mark@staffcircle.com", "verified": false}, "http://www.linkedin.com/in/guenard": {"email": "antoine@batch.com", "verified": false}, "http://www.linkedin.com/in/mohan-doshi-27a0817": {"email": "mohandoshi@ninestars.in", "verified": false}, "http://www.linkedin.com/in/jeyaprakash-xavier": {"email": "jeyaprakash@ninestars.in", "verified": false}, "http://www.linkedin.com/in/mikcons": {"email": "mik.cons@moneyinfo.com", "verified": false}, "http://www.linkedin.com/in/james-brosse-0691809b": {"email": "", "verified": false}, "http://www.linkedin.com/in/david-s-kane": {"email": "dave@aimhi.earth", "verified": false}, "http://www.linkedin.com/in/hugobenzaida": {"email": "hugo@uptale.io", "verified": false}, "http://www.linkedin.com/in/herve-lourdin-234760": {"email": "herve@batch.com", "verified": false}, "http://www.linkedin.com/in/paulshepherd1975": {"email": "paul@wbb.ai", "verified": false}, "http://www.linkedin.com/in/pierre-philippe-avril-9b039968": {"email": "pierre@uptale.io", "verified": false}, "http://www.linkedin.com/in/tomas-ds-aguiar": {"email": "t.aguiar@innoloft.com", "verified": false}, "http://www.linkedin.com/in/yohann-merran": {"email": "yohann@angelspartners.com", "verified": false}, "http://www.linkedin.com/in/r%c3%a9mi-ferrez-182b99105": {"email": "remi@batch.com", "verified": false}, "http://www.linkedin.com/in/robert-greene-390712170": {"email": "", "verified": false}, "http://www.linkedin.com/in/robertjohngough": {"email": "", "verified": false}, "http://www.linkedin.com/in/kim-soon-goh-82b8753": {"email": "", "verified": false}, "http://www.linkedin.com/in/thomasloup": {"email": "thomas.loup@batch.com", "verified": false}, "http://www.linkedin.com/in/jarronaizen": {"email": "jarron.aizen@hapana.com", "verified": false}, "http://www.linkedin.com/in/benwilliamson": {"email": "ben.williamson@investorhub.com", "verified": false}, "http://www.linkedin.com/in/rhysldavis": {"email": "rhys@investorhub.com", "verified": false}, "http://www.linkedin.com/in/riddhi-mazumdar-629a299": {"email": "riddhi@cadmus.io", "verified": false}, "http://www.linkedin.com/in/hansmina": {"email": "hans@weareinnoit.com", "verified": false}, "http://www.linkedin.com/in/travis-shannon": {"email": "travis.shannon@hapana.com", "verified": false}, "http://www.linkedin.com/in/jos%c3%a9-miguel-cantero-ruiz-83141966": {"email": "josemiguel@genially.com", "verified": false}, "http://www.linkedin.com/in/jos%c3%a9-luis-fern%c3%a1ndez-72516783": {"email": "joseluis@hanzo.es", "verified": false}, "http://www.linkedin.com/in/jimmy-qiu-b75ab293": {"email": "jimmy@investorhub.com", "verified": false}, "http://www.linkedin.com/in/alansach": {"email": "alan.sacharowitz@hapana.com", "verified": false}, "http://www.linkedin.com/in/benjamincochrane": {"email": "ben.cochrane@hapana.com", "verified": false}, "http://www.linkedin.com/in/cristina-g%c3%b3mez-prada-8571a63": {"email": "cristina@hanzo.es", "verified": false}, "http://www.linkedin.com/in/rubencogollor": {"email": "ruben@hanzo.es", "verified": false}, "http://www.linkedin.com/in/andyfeltham": {"email": "andy@logicdialog.ai", "verified": false}, "http://www.linkedin.com/in/amanda-ames-053b8512": {"email": "", "verified": false}, "http://www.linkedin.com/in/manuel-vida-carri%c3%b3n-28aa582a": {"email": "manuel@genially.com", "verified": false}, "http://www.linkedin.com/in/miguelleogarcia": {"email": "miguel@ideawisegroup.com", "verified": false}, "http://www.linkedin.com/in/alberto-a-robles-98a341b": {"email": "", "verified": false}, "http://www.linkedin.com/in/alaaashkar": {"email": "alaa@apliman.com", "verified": false}, "http://www.linkedin.com/in/gopalagrawal": {"email": "gopal.agrawal@hapana.com", "verified": false}, "http://www.linkedin.com/in/dorukmutlu": {"email": "doruk@evam.com", "verified": false}, "http://www.linkedin.com/in/jos%c3%a9-guerrero-6577071a4": {"email": "", "verified": false}, "http://www.linkedin.com/in/carlos-andres-velez-lopez-57355346": {"email": "carloslopez@comfama.com.co", "verified": false}, "http://www.linkedin.com/in/daniellerustice": {"email": "", "verified": false}, "http://www.linkedin.com/in/fablacer": {"email": "fabio.lacerda@blip.ai", "verified": false}, "http://www.linkedin.com/in/f-armentano": {"email": "facundo@leadgenios.com", "verified": false}, "http://www.linkedin.com/in/andersonfonseca": {"email": "anderson.fonseca@blip.ai", "verified": false}, "http://www.linkedin.com/in/thiago-nigro": {"email": "thiago.nigro@timeprimo.com", "verified": false}, "http://www.linkedin.com/in/helenabello": {"email": "helena.bello@blip.ai", "verified": false}, "http://www.linkedin.com/in/emin-ozden": {"email": "emin@evam.com", "verified": false}, "http://www.linkedin.com/in/candas-guler-97a279243": {"email": "candas@evam.com", "verified": false}, "http://www.linkedin.com/in/gokayakin": {"email": "gokayakin@ogoodigital.com", "verified": false}, "http://www.linkedin.com/in/onur-yavuz-94007628": {"email": "onur@kunduz.com", "verified": false}, "http://www.linkedin.com/in/leandro-couretot": {"email": "", "verified": false}, "http://www.linkedin.com/in/renatodiassilva": {"email": "renato.dias@ambevtech.com.br", "verified": false}, "http://www.linkedin.com/in/aaoliver": {"email": "anderson@timeprimo.com", "verified": false}, "http://www.linkedin.com/in/marcelo-de-almeida-milani-87a790102": {"email": "", "verified": false}, "http://www.linkedin.com/in/adrianoskam": {"email": "adrian@kplr.mx", "verified": false}, "http://www.linkedin.com/in/gabrielbfcampos": {"email": "gabriel.campos@blip.ai", "verified": false}, "http://www.linkedin.com/in/berkayakbas": {"email": "berkay@kunduz.com", "verified": false}, "http://www.linkedin.com/in/valeriagolinoski": {"email": "valeria.golinoski@ambevtech.com.br", "verified": false}, "http://www.linkedin.com/in/michelinepimenta": {"email": "micheline.pimenta@ambevtech.com.br", "verified": false}, "http://www.linkedin.com/in/larissa-marchi": {"email": "larissa.marchi@ambevtech.com.br", "verified": false}, "http://www.linkedin.com/in/guilhermevini": {"email": "", "verified": false}, "http://www.linkedin.com/in/ishvannvillate": {"email": "ishvann.larsen@blip.ai", "verified": false}, "http://www.linkedin.com/in/leticiarezendes": {"email": "lr@opco-sante.fr", "verified": false}, "http://www.linkedin.com/in/matheusvillar": {"email": "matheus.villar@timeprimo.com", "verified": false}, "http://www.linkedin.com/in/victor-marcel-5414232b": {"email": "", "verified": false}, "http://www.linkedin.com/in/cristiansoto": {"email": "cristian.soto@gointegro.com", "verified": false}, "http://www.linkedin.com/in/luismorenoisamit": {"email": "luis.moreno@gointegro.com", "verified": false}, "http://www.linkedin.com/in/lionelmedori": {"email": "lionel.medori@gointegro.com", "verified": false}, "http://www.linkedin.com/in/diegofabri": {"email": "", "verified": false}, "http://www.linkedin.com/in/agustina-bamba": {"email": "agustina@gruponods.com", "verified": false}, "http://www.linkedin.com/in/mar%c3%ada-florencia-tarantola-475b2222": {"email": "florencia.tarantola@gointegro.com", "verified": false}, "http://www.linkedin.com/in/rafael-cs": {"email": "", "verified": false}}